add_methods_and_properties_to_existing_object/LICENSE
add_methods_and_properties_to_existing_object/README.MD
add_methods_and_properties_to_existing_object/__init__.py
add_methods_and_properties_to_existing_object/requirements.txt
add_methods_and_properties_to_existing_object/thirdparty.json
add_methods_and_properties_to_existing_object-0.10.dist-info/LICENSE.rst
add_methods_and_properties_to_existing_object-0.10.dist-info/METADATA
add_methods_and_properties_to_existing_object-0.10.dist-info/WHEEL
add_methods_and_properties_to_existing_object-0.10.dist-info/top_level.txt
add_methods_and_properties_to_existing_object-0.10.dist-info/RECORD
